sbsv/__init__.py
sbsv/sbsv.py
sbsv/utils.py
sbsv-0.1.2.dist-info/METADATA
sbsv-0.1.2.dist-info/WHEEL
sbsv-0.1.2.dist-info/licenses/LICENSE
sbsv-0.1.2.dist-info/RECORD
