Metadata-Version: 2.4
Name: sbsv
Version: 0.1.2
Summary: SBSV: Square Brackets Separated Values
Project-URL: Homepage, https://github.com/hsh814/sbsv
Project-URL: Issues, https://github.com/hsh814/sbsv/issues
Author-email: Seungheon Han <shhan814@gmail.com>
License-File: LICENSE
Classifier: License :: OSI Approved :: MIT License
Classifier: Operating System :: OS Independent
Classifier: Programming Language :: Python :: 3
Requires-Python: >=3.6
